tensorflow_modules/__init__.py
tensorflow_modules/mask/__init__.py
tensorflow_modules/mask/test_util.py
tensorflow_modules/mask/util.py
tensorflow_modules/multi_head_attention/__init__.py
tensorflow_modules/multi_head_attention/attention.py
tensorflow_modules/multi_head_attention/model.py
tensorflow_modules/multi_head_attention/test_attention.py
tensorflow_modules/reversible_transformer/__init__.py
tensorflow_modules/reversible_transformer/multi_head_attention_layer.py
tensorflow_modules/reversible_transformer/reversible_decoder_layer.py
tensorflow_modules/reversible_transformer/reversible_encoder_layer.py
tensorflow_modules/transformer/__init__.py
tensorflow_modules/transformer/decoder.py
tensorflow_modules/transformer/decoder_layer.py
tensorflow_modules/transformer/encoder.py
tensorflow_modules/transformer/encoder_layer.py
tensorflow_modules/transformer/point_wise_feed_forward_network.py
tensorflow_modules/transformer/test_decoder.py
tensorflow_modules/transformer/test_encoder.py
tests/__init__.py
tests/mask/__init__.py
tests/mask/test_util.py
tests/multi_head_attention/__init__.py
tests/multi_head_attention/test_attention.py
tests/reversible_transformer/__init__.py
tests/reversible_transformer/test_multi_head_attention_layer.py
tests/reversible_transformer/test_reversible_decoder_layer.py
tests/reversible_transformer/test_reversible_encoder_layer.py
tests/transformer/__init__.py
tests/transformer/test_decoder.py
tests/transformer/test_decoder_layer.py
tests/transformer/test_encoder.py
tests/transformer/test_encoder_layer.py
tensorflow_modules-0.0.8.dist-info/LICENSE
tensorflow_modules-0.0.8.dist-info/METADATA
tensorflow_modules-0.0.8.dist-info/WHEEL
tensorflow_modules-0.0.8.dist-info/top_level.txt
tensorflow_modules-0.0.8.dist-info/RECORD
