Metadata-Version: 2.1
Name: tensorflow-modules
Version: 0.0.8
Summary: tensorflow layers, models
Home-page: https://github.com/otsuka-kentaro/tensorflow-modules
Author: OtsukaKentaro
Author-email: otsuka.kenchan@gmail.com
License: UNKNOWN
Platform: UNKNOWN
Classifier: Programming Language :: Python :: 3
Classifier: License :: OSI Approved :: MIT License
Classifier: Operating System :: OS Independent
Requires-Python: >=3.8
Requires-Dist: tensorflow (==2.4.1)
